README.rst
setup.py
pki_client/__init__.py
pki_client/cli.py
pki_client/core.py
pki_client/crypto.py
pki_client.egg-info/PKG-INFO
pki_client.egg-info/SOURCES.txt
pki_client.egg-info/dependency_links.txt
pki_client.egg-info/entry_points.txt
pki_client.egg-info/not-zip-safe
pki_client.egg-info/requires.txt
pki_client.egg-info/top_level.txt